creso/__init__.py
creso/classifier.py
creso/cli.py
creso/config.py
creso/constants.py
creso/cross_validation.py
creso/diagnostics.py
creso/exceptions.py
creso/layers.py
creso/logging.py
creso/metrics.py
creso/model.py
creso/performance.py
creso/py.typed
creso/regressor.py
creso/trainer.py
creso/utils.py
creso/validation.py
creso/version.py
creso/visualization.py
creso/wave_model.py
creso/wave_physics.py
creso/adapters/__init__.py
creso/adapters/graph.py
creso/adapters/timeseries.py
creso-0.1.0.dist-info/licenses/LICENSE
creso-0.1.0.dist-info/METADATA
creso-0.1.0.dist-info/WHEEL
creso-0.1.0.dist-info/entry_points.txt
creso-0.1.0.dist-info/top_level.txt
creso-0.1.0.dist-info/RECORD
