Metadata-Version: 2.4
Name: creso
Version: 0.1.0
Summary: Coherent Resonant Spectral Operator (CReSO) - Lightweight spectral neural networks
Home-page: https://github.com/bay0/creso
Author: bay0
Author-email: 
License: Apache-2.0
Project-URL: Homepage, https://github.com/bay0/creso
Project-URL: Repository, https://github.com/bay0/creso
Project-URL: Documentation, https://creso-project.github.io/creso
Project-URL: Issues, https://github.com/bay0/creso/issues
Project-URL: Changelog, https://github.com/bay0/creso/blob/main/CHANGELOG.md
Keywords: machine learning,neural networks,spectral methods,fourier features,pytorch,time series,graph neural networks
Classifier: Development Status :: 4 - Beta
Classifier: Intended Audience :: Science/Research
Classifier: Intended Audience :: Developers
Classifier: License :: OSI Approved :: Apache Software License
Classifier: Operating System :: OS Independent
Classifier: Programming Language :: Python :: 3
Classifier: Programming Language :: Python :: 3.8
Classifier: Programming Language :: Python :: 3.9
Classifier: Programming Language :: Python :: 3.10
Classifier: Programming Language :: Python :: 3.11
Classifier: Programming Language :: Python :: 3.12
Classifier: Topic :: Scientific/Engineering :: Artificial Intelligence
Classifier: Topic :: Software Development :: Libraries :: Python Modules
Requires-Python: >=3.8
License-File: LICENSE
Requires-Dist: torch>=2.0.0
Requires-Dist: numpy>=1.23.0
Requires-Dist: scikit-learn>=1.1.0
Requires-Dist: tqdm>=4.64.0
Provides-Extra: graph
Requires-Dist: scipy>=1.9.0; extra == "graph"
Provides-Extra: cli
Requires-Dist: hydra-core>=1.3.0; extra == "cli"
Requires-Dist: omegaconf>=2.3.0; extra == "cli"
Provides-Extra: dev
Requires-Dist: pytest>=7.0.0; extra == "dev"
Requires-Dist: pytest-cov>=4.0.0; extra == "dev"
Requires-Dist: black>=22.0.0; extra == "dev"
Requires-Dist: ruff>=0.1.0; extra == "dev"
Requires-Dist: mypy>=1.0.0; extra == "dev"
Requires-Dist: pre-commit>=2.20.0; extra == "dev"
Requires-Dist: tqdm>=4.64.0; extra == "dev"
Requires-Dist: onnx>=1.12.0; extra == "dev"
Requires-Dist: onnxruntime>=1.12.0; extra == "dev"
Provides-Extra: docs
Requires-Dist: sphinx>=5.0.0; extra == "docs"
Requires-Dist: sphinx-rtd-theme>=1.2.0; extra == "docs"
Requires-Dist: myst-parser>=0.18.0; extra == "docs"
Provides-Extra: viz
Requires-Dist: matplotlib>=3.5.0; extra == "viz"
Requires-Dist: seaborn>=0.11.0; extra == "viz"
Provides-Extra: export
Requires-Dist: onnx>=1.12.0; extra == "export"
Requires-Dist: onnxruntime>=1.12.0; extra == "export"
Provides-Extra: all
Requires-Dist: creso[cli,export,graph,viz]; extra == "all"
Provides-Extra: dev-all
Requires-Dist: creso[all,dev]; extra == "dev-all"
Dynamic: license-file
